slimrr/__init__.py
slimrr/euler.py
slimrr/integer.py
slimrr/matrix33.py
slimrr/matrix44.py
slimrr/quaternion.py
slimrr/trig.py
slimrr/utils.py
slimrr/vector.py
slimrr/vector2.py
slimrr/vector3.py
slimrr/vector4.py
slimrr/version.py
slimrr/objects/__init__.py
slimrr/objects/base.py
slimrr/objects/matrix33.py
slimrr/objects/matrix44.py
slimrr/objects/quaternion.py
slimrr/objects/vector2.py
slimrr/objects/vector3.py
slimrr/objects/vector4.py
slimrr-0.1.1.dist-info/LICENSE
slimrr-0.1.1.dist-info/METADATA
slimrr-0.1.1.dist-info/WHEEL
slimrr-0.1.1.dist-info/top_level.txt
slimrr-0.1.1.dist-info/RECORD
