Metadata-Version: 2.2
Name: slimrr
Version: 0.1.1
Summary: 2D+3D math functions using NumPy
Home-page: https://github.com/takeiteasy/slimrr
Author: George Watson
Author-email: George Watson <gigolo@hotmail.co.uk>
License: BSD
Project-URL: Homepage, https://github.com/takeiteasy/slimrr
Project-URL: Issues, https://github.com/takeiteasy/slimrr/issues
Platform: any
Classifier: Natural Language :: English
Classifier: Intended Audience :: Developers
Classifier: Operating System :: MacOS :: MacOS X
Classifier: Operating System :: Microsoft :: Windows
Classifier: Operating System :: POSIX
Classifier: Programming Language :: Python
Classifier: License :: OSI Approved :: BSD License
Classifier: Topic :: Multimedia :: Graphics
Classifier: Topic :: Scientific/Engineering :: Mathematics
Classifier: Topic :: Software Development :: Libraries
Classifier: Topic :: Software Development :: Libraries :: Python Modules
Requires-Python: >=3.8
License-File: LICENSE
Requires-Dist: numpy
Requires-Dist: multipledispatch
Dynamic: author
Dynamic: home-page
Dynamic: platform
